setup.py
rst/__init__.py
rst/animation/BinocularHeadGaze_pb2.py
rst/animation/EmotionExpression_pb2.py
rst/animation/HeadAnimation_pb2.py
rst/animation/__init__.py
rst/audition/PhonemeCollection_pb2.py
rst/audition/Phoneme_pb2.py
rst/audition/SoundChunkCollection_pb2.py
rst/audition/SoundChunk_pb2.py
rst/audition/Utterance_pb2.py
rst/audition/__init__.py
rst/bayesnetwork/BayesNetworkEvidence_pb2.py
rst/bayesnetwork/BayesNetwork_pb2.py
rst/bayesnetwork/BayesVariable_pb2.py
rst/bayesnetwork/__init__.py
rst/calendar/Attendee_pb2.py
rst/calendar/CalendarComponents_pb2.py
rst/calendar/CalendarList_pb2.py
rst/calendar/CalendarQueryResult_pb2.py
rst/calendar/CalendarQuery_pb2.py
rst/calendar/CalendarUpdate_pb2.py
rst/calendar/DateTime_pb2.py
rst/calendar/Entry_pb2.py
rst/calendar/Event_pb2.py
rst/calendar/Observance_pb2.py
rst/calendar/Organizer_pb2.py
rst/calendar/RecurrenceId_pb2.py
rst/calendar/RecurrenceRule_pb2.py
rst/calendar/Recurrence_pb2.py
rst/calendar/Relationship_pb2.py
rst/calendar/RequestStatus_pb2.py
rst/calendar/TimeZone_pb2.py
rst/calendar/Todo_pb2.py
rst/calendar/__init__.py
rst/classification/ClassificationResultMap_pb2.py
rst/classification/ClassificationResult_pb2.py
rst/classification/ClassificationResults_pb2.py
rst/classification/ClassifiedRegion2D_pb2.py
rst/classification/ClassifiedRegion3D_pb2.py
rst/classification/ClassifiedRegions2D_pb2.py
rst/classification/ClassifiedRegions3D_pb2.py
rst/classification/__init__.py
rst/communicationpatterns/TaskStateCollection_pb2.py
rst/communicationpatterns/TaskState_pb2.py
rst/communicationpatterns/__init__.py
rst/devices/__init__.py
rst/devices/generic/BatteryStateCollection_pb2.py
rst/devices/generic/BatteryState_pb2.py
rst/devices/generic/CpuStateCollection_pb2.py
rst/devices/generic/CpuState_pb2.py
rst/devices/generic/DiskStateCollection_pb2.py
rst/devices/generic/DiskState_pb2.py
rst/devices/generic/HostInformationCollection_pb2.py
rst/devices/generic/HostInformation_pb2.py
rststable.egg-info/PKG-INFO
rststable.egg-info/SOURCES.txt
rststable.egg-info/dependency_links.txt
rststable.egg-info/requires.txt
rststable.egg-info/top_level.txt