Metadata-Version: 1.0
Name: rststable
Version: 0.16.3
Summary: Robotics Systems Types
Home-page: https://code.cor-lab.org/projects/rst
Author: Johannes Wienke
Author-email: jwienke@techfak.uni-bielefeld.de
License: GPLv3
Platform: UNKNOWN
